adc_parallel.vhdl
-- Aufgabe 1: Prioritaetsdecoder
-- Decoder entsprechend der Tabelle beim ADU
LIBRARY ieee;
USE ieee.std_logic_1164.ALL;

ENTITY adc_parallel IS
    PORT (
        inputVoltage : IN std_logic_vector(6 DOWNTO 0);
        outputVoltage : OUT std_logic_vector(2 DOWNTO 0)
    );
END adc_parallel;

ARCHITECTURE behave OF adc_parallel IS
BEGIN
    WITH inputVoltage SELECT
        outputVoltage <= "000" WHEN "0000000",
        "001" WHEN "0000001",
        "010" WHEN "0000011",
        "011" WHEN "0000111",
        "100" WHEN "0001111",
        "101" WHEN "0011111",
        "110" WHEN "0111111",
        "111" WHEN "1111111",
        "000" WHEN OTHERS;
END behave;

adc_parallel_tb.vhdl
LIBRARY ieee;
USE ieee.std_logic_1164.ALL;

ENTITY adc_parallel_test IS
END adc_parallel_test;

ARCHITECTURE test OF adc_parallel_test IS
    COMPONENT adc_parallel IS
        PORT (
            inputVoltage : IN std_logic_vector(6 DOWNTO 0);
            outputVoltage : OUT std_logic_vector(2 DOWNTO 0)
        );
    END COMPONENT;

    SIGNAL inputVoltage : std_logic_vector(6 DOWNTO 0);
    SIGNAL outputVoltage : std_logic_vector(2 DOWNTO 0);

BEGIN
    adc_parallel_pr : adc_parallel PORT MAP
        (inputVoltage => inputVoltage);

    PROCESS BEGIN
        inputVoltage <= "0000000";
        WAIT FOR 1 ns;
        inputVoltage <= "0000001";
        WAIT FOR 1 ns;
        inputVoltage <= "0000011";
        WAIT FOR 1 ns;
        inputVoltage <= "0000111";
        WAIT FOR 1 ns;
        inputVoltage <= "0001111";
        WAIT FOR 1 ns;
        inputVoltage <= "0011111";
        WAIT FOR 1 ns;
        inputVoltage <= "0111111";
        WAIT FOR 1 ns;
        inputVoltage <= "1111111";
        WAIT FOR 1 ns;

		-- ASSERT false REPORT "Reached end of test";
        wait;
    END PROCESS;
END test;

adc_parallel.vcd
$date
  Sat Aug 22 15:21:32 2020
$end
$version
  GHDL v0
$end
$timescale
  1 fs
$end
$scope module standard $end
$upscope $end
$scope module std_logic_1164 $end
$upscope $end
$scope module adc_parallel_test $end
$var reg 7 ! inputvoltage[6:0] $end
$var reg 3 " outputvoltage[2:0] $end
$scope module adc_parallel_pr $end
$var reg 7 # inputvoltage[6:0] $end
$var reg 3 $ outputvoltage[2:0] $end
$upscope $end
$upscope $end
$enddefinitions $end
#0
b0000000 !
bUUU "
b0000000 #
b000 $
#1000000
b0000001 !
b0000001 #
b001 $
#2000000
b0000011 !
b0000011 #
b010 $
#3000000
b0000111 !
b0000111 #
b011 $
#4000000
b0001111 !
b0001111 #
b100 $
#5000000
b0011111 !
b0011111 #
b101 $
#6000000
b0111111 !
b0111111 #
b110 $
#7000000
b1111111 !
b1111111 #
b111 $
