ampel_loesung.vhdl
LIBRARY ieee;
USE ieee.std_logic_1164.ALL;
USE ieee.numeric_std.ALL;

ENTITY ampel IS PORT (
    clk, r_neg : IN std_logic; -- r_neg = reset nicht
    gruen_h, rot_h, gelb_h, gruen_n, rot_n, gelb_n : OUT std_logic);
END ampel;

ARCHITECTURE verhalten OF ampel IS -- Architektur mit 2 Prozessen
    SIGNAL zaehl : unsigned(3 DOWNTO 0); -- interner Zaehler
BEGIN
    zaehler : PROCESS (r_neg, clk) -- Prozess zur Modellierung des Zaehlers
    BEGIN
        IF r_neg = '0' THEN
            zaehl <= "0000"; -- asynchroner Reset
        ELSIF (clk'event AND clk = '1') THEN
            zaehl <= zaehl + 1;
        END IF;
    END PROCESS zaehler;

    ausgabe : PROCESS (zaehl) -- Prozess fuer die Ausgabe
    BEGIN
        IF (zaehl < "0111") THEN
            gruen_h <= '1';
            rot_h <= '0';
            gelb_h <= '0';
            gruen_n <= '0';
            rot_n <= '1';
            gelb_n <= '0';
        ELSIF (zaehl = "0111") THEN
            gruen_h <= '0';
            rot_h <= '0';
            gelb_h <= '1';
            gruen_n <= '0';
            rot_n <= '1';
            gelb_n <= '0';
        ELSIF (zaehl = "1000") THEN
            gruen_h <= '0';
            rot_h <= '1';
            gelb_h <= '0';
            gruen_n <= '0';
            rot_n <= '1';
            gelb_n <= '0';
        ELSIF (zaehl = "1001") THEN
            gruen_h <= '0';
            rot_h <= '1';
            gelb_h <= '0';
            gruen_n <= '0';
            rot_n <= '1';
            gelb_n <= '1';
        ELSIF (zaehl > "1001" AND zaehl < "1101") THEN
            gruen_h <= '0';
            rot_h <= '1';
            gelb_h <= '0';
            gruen_n <= '1';
            rot_n <= '0';
            gelb_n <= '0';
        ELSIF (zaehl = "1101") THEN
            gruen_h <= '0';
            rot_h <= '1';
            gelb_h <= '0';
            gruen_n <= '0';
            rot_n <= '0';
            gelb_n <= '1';
        ELSIF (zaehl = "1110") THEN
            gruen_h <= '0';
            rot_h <= '1';
            gelb_h <= '0';
            gruen_n <= '0';
            rot_n <= '1';
            gelb_n <= '0';
        ELSIF (zaehl = "1111") THEN
            gruen_h <= '0';
            rot_h <= '1';
            gelb_h <= '1';
            gruen_n <= '0';
            rot_n <= '1';
            gelb_n <= '0';
        END IF;
    END PROCESS ausgabe;
END verhalten;

ampel_loesung_tb.vhdl
LIBRARY ieee;
USE ieee.std_logic_1164.ALL;

ENTITY ampel_tb IS
END ampel_tb;

ARCHITECTURE test OF ampel_tb IS
	COMPONENT ampel
		PORT (
			clk, r_neg : IN std_logic;
			gruen_h, rot_h, gelb_h, gruen_n, rot_n, gelb_n : OUT std_logic
		);
	END COMPONENT;

	SIGNAL clk, r_neg, gruen_h, rot_h, gelb_h, gruen_n, rot_n, gelb_n : std_logic;

BEGIN
	ampel_steuer : ampel PORT MAP(clk => clk, r_neg => r_neg, gruen_h => gruen_h, rot_h => rot_h, gelb_h => gelb_h, gruen_n => gruen_n, rot_n => rot_n, gelb_n => gelb_n);

	PROCESS BEGIN
		clk <= '0';
		r_neg <= '0';
		WAIT FOR 1000 ms;
		clk <= '1';
		r_neg <= '0';
		WAIT FOR 1000 ms;
		clk <= '0';
		r_neg <= '1';
		WAIT FOR 1000 ms;
		clk <= '1';
		r_neg <= '1';
		WAIT FOR 1000 ms;
		clk <= '0';
		r_neg <= '1';
		WAIT FOR 1000 ms;
		clk <= '1';
		r_neg <= '1';
		WAIT FOR 1000 ms;
		clk <= '0';
		r_neg <= '1';
		WAIT FOR 1000 ms;
		clk <= '1';
		r_neg <= '1';
		WAIT FOR 1000 ms;
		clk <= '0';
		r_neg <= '1';
		WAIT FOR 1000 ms;
		clk <= '1';
		r_neg <= '1';
		WAIT FOR 1000 ms;
		clk <= '0';
		r_neg <= '1';
		WAIT FOR 1000 ms;
		clk <= '1';
		r_neg <= '1';
		WAIT FOR 1000 ms;
		clk <= '0';
		r_neg <= '1';
		WAIT FOR 1000 ms;
		clk <= '1';
		r_neg <= '1';
		WAIT FOR 1000 ms;
		clk <= '0';
		r_neg <= '1';
		WAIT FOR 1000 ms;
		clk <= '1';
		r_neg <= '1';
		WAIT FOR 1000 ms;
		clk <= '0';
		r_neg <= '1';
		WAIT FOR 1000 ms;
		clk <= '1';
		r_neg <= '1';
		WAIT FOR 1000 ms;
		clk <= '0';
		r_neg <= '1';
		WAIT FOR 1000 ms;
		clk <= '1';
		r_neg <= '1';
		WAIT FOR 1000 ms;
		clk <= '0';
		r_neg <= '1';
		WAIT FOR 1000 ms;
		clk <= '1';
		r_neg <= '1';
		WAIT FOR 1000 ms;
		clk <= '0';
		r_neg <= '1';
		clk <= '0';
		r_neg <= '1';
		WAIT FOR 1000 ms;
		clk <= '1';
		r_neg <= '1';
		WAIT FOR 1000 ms;
		clk <= '0';
		r_neg <= '1';
		WAIT FOR 1000 ms;
		clk <= '1';
		r_neg <= '1';
		WAIT FOR 1000 ms;
		clk <= '0';
		r_neg <= '1';
		WAIT FOR 1000 ms;
		clk <= '1';
		r_neg <= '1';
		WAIT FOR 1000 ms;
		clk <= '0';
		r_neg <= '1';
		WAIT FOR 1000 ms;
		clk <= '1';
		r_neg <= '1';
		WAIT FOR 1000 ms;
		clk <= '0';
		r_neg <= '1';
		WAIT FOR 1000 ms;
		clk <= '1';
		r_neg <= '1';
		WAIT FOR 1000 ms;
		clk <= '0';
		r_neg <= '1';
		WAIT FOR 1000 ms;
		clk <= '1';
		r_neg <= '1';
		WAIT FOR 1000 ms;
		clk <= '0';
		r_neg <= '1';
		WAIT FOR 1000 ms;
		clk <= '1';
		r_neg <= '1';
		WAIT FOR 1000 ms;
		clk <= '0';
		r_neg <= '1';
		WAIT FOR 1000 ms;
		clk <= '1';
		r_neg <= '1';
		WAIT FOR 1000 ms;
		clk <= '0';
		r_neg <= '1';
		WAIT FOR 1000 ms;
		clk <= '1';
		r_neg <= '1';
		WAIT FOR 1000 ms;
		clk <= '0';
		r_neg <= '1';
		WAIT FOR 1000 ms;
		clk <= '1';
		r_neg <= '1';
		WAIT FOR 1000 ms;
		clk <= '0';
		r_neg <= '1';
		WAIT FOR 1000 ms;
		clk <= '1';
		r_neg <= '1';
		WAIT FOR 1000 ms;
		clk <= '0';
		r_neg <= '1';
		ASSERT false REPORT "Reached end of test";
		WAIT;
	END PROCESS;
END test;

ampel_loesung.vcd
$date
  Sun Aug 23 14:51:33 2020
$end
$version
  GHDL v0
$end
$timescale
  1 fs
$end
$scope module standard $end
$upscope $end
$scope module std_logic_1164 $end
$upscope $end
$scope module numeric_std $end
$upscope $end
$scope module ampel_tb $end
$var reg 1 ! clk $end
$var reg 1 " r_neg $end
$var reg 1 # gruen_h $end
$var reg 1 $ rot_h $end
$var reg 1 % gelb_h $end
$var reg 1 & gruen_n $end
$var reg 1 ' rot_n $end
$var reg 1 ( gelb_n $end
$scope module ampel_steuer $end
$var reg 1 ) clk $end
$var reg 1 * r_neg $end
$var reg 1 + gruen_h $end
$var reg 1 , rot_h $end
$var reg 1 - gelb_h $end
$var reg 1 . gruen_n $end
$var reg 1 / rot_n $end
$var reg 1 0 gelb_n $end
$var reg 4 1 zaehl[3:0] $end
$upscope $end
$upscope $end
$enddefinitions $end
#0
0!
0"
1#
0$
0%
0&
1'
0(
0)
0*
1+
0,
0-
0.
1/
00
b0000 1
#1000000000000000
1!
1)
#2000000000000000
0!
1"
0)
1*
#3000000000000000
1!
1)
b0001 1
#4000000000000000
0!
0)
#5000000000000000
1!
1)
b0010 1
#6000000000000000
0!
0)
#7000000000000000
1!
1)
b0011 1
#8000000000000000
0!
0)
#9000000000000000
1!
1)
b0100 1
#10000000000000000
0!
0)
#11000000000000000
1!
1)
b0101 1
#12000000000000000
0!
0)
#13000000000000000
1!
1)
b0110 1
#14000000000000000
0!
0)
#15000000000000000
1!
0#
1%
1)
0+
1-
b0111 1
#16000000000000000
0!
0)
#17000000000000000
1!
1$
0%
1)
1,
0-
b1000 1
#18000000000000000
0!
0)
#19000000000000000
1!
1(
1)
10
b1001 1
#20000000000000000
0!
0)
#21000000000000000
1!
1&
0'
0(
1)
1.
0/
00
b1010 1
#22000000000000000
0!
0)
#23000000000000000
1!
1)
b1011 1
#24000000000000000
0!
0)
#25000000000000000
1!
1)
b1100 1
#26000000000000000
0!
0)
#27000000000000000
1!
0&
1(
1)
0.
10
b1101 1
#28000000000000000
0!
0)
#29000000000000000
1!
1'
0(
1)
1/
00
b1110 1
#30000000000000000
0!
0)
#31000000000000000
1!
1%
1)
1-
b1111 1
#32000000000000000
0!
0)
#33000000000000000
1!
1#
0$
0%
1)
1+
0,
0-
b0000 1
#34000000000000000
0!
0)
#35000000000000000
1!
1)
b0001 1
#36000000000000000
0!
0)
#37000000000000000
1!
1)
b0010 1
#38000000000000000
0!
0)
#39000000000000000
1!
1)
b0011 1
#40000000000000000
0!
0)
#41000000000000000
1!
1)
b0100 1
#42000000000000000
0!
0)
#43000000000000000
1!
1)
b0101 1
