prioDecoder.vhdl
-- Aufgabe 1: Prioritaetsdecoder
-- Decoder entsprechend der Tabelle beim ADU
LIBRARY ieee;
USE ieee.std_logic_1164.ALL;

ENTITY prioDecoder IS
	PORT (
		Ein : IN std_logic_vector(6 DOWNTO 0);
		Aus : OUT std_logic_vector(2 DOWNTO 0));
END prioDecoder;

ARCHITECTURE Verhalten OF prioDecoder IS
BEGIN
	WITH Ein SELECT
		Aus <= "000" WHEN "0000000",
		"001" WHEN "0000001",
		"010" WHEN "0000011",
		"011" WHEN "0000111",
		"100" WHEN "0001111",
		"101" WHEN "0011111",
		"110" WHEN "0111111",
		"111" WHEN "1111111",
		"000" WHEN OTHERS;
END Verhalten;

prioDecoder_tb.vhdl
LIBRARY ieee;
USE ieee.std_logic_1164.ALL;

ENTITY prioDecoder_tb IS
END prioDecoder_tb;

ARCHITECTURE test OF prioDecoder_tb IS
	COMPONENT prioDecoder
		PORT (
			Ein : IN std_logic_vector(6 DOWNTO 0);
			Aus : OUT std_logic_vector(2 DOWNTO 0)
		);
	END COMPONENT;

	SIGNAL Ein : std_logic_vector(6 DOWNTO 0) := "0000000";
	SIGNAL Aus : std_logic_vector(2 DOWNTO 0);

BEGIN
	prio_decoder : prioDecoder PORT MAP(Ein => Ein, Aus => Aus);

	PROCESS BEGIN
		Ein <= "0000000";
		WAIT FOR 1 ns;
		Ein <= "0000001";
		WAIT FOR 1 ns;
		Ein <= "0000011";
		WAIT FOR 1 ns;
		Ein <= "0000111";
		WAIT FOR 1 ns;
		Ein <= "0001111";
		WAIT FOR 1 ns;
		Ein <= "0011111";
		WAIT FOR 1 ns;
		Ein <= "0111111";
		WAIT FOR 1 ns;
		Ein <= "1111111";
		WAIT FOR 1 ns;

		ASSERT false REPORT "Reached end of test";
		WAIT;
	END PROCESS;
END test;

prioDecoder.vcd
$date
  Sat Aug 22 15:14:56 2020
$end
$version
  GHDL v0
$end
$timescale
  1 fs
$end
$scope module standard $end
$upscope $end
$scope module std_logic_1164 $end
$upscope $end
$scope module priodecoder_tb $end
$var reg 7 ! ein[6:0] $end
$var reg 3 " aus[2:0] $end
$scope module prio_decoder $end
$var reg 7 # ein[6:0] $end
$var reg 3 $ aus[2:0] $end
$upscope $end
$upscope $end
$enddefinitions $end
#0
b0000000 !
b000 "
b0000000 #
b000 $
#1000000
b0000001 !
b001 "
b0000001 #
b001 $
#2000000
b0000011 !
b010 "
b0000011 #
b010 $
#3000000
b0000111 !
b011 "
b0000111 #
b011 $
#4000000
b0001111 !
b100 "
b0001111 #
b100 $
#5000000
b0011111 !
b101 "
b0011111 #
b101 $
#6000000
b0111111 !
b110 "
b0111111 #
b110 $
#7000000
b1111111 !
b111 "
b1111111 #
b111 $
