sipo.vhdl
library ieee;
use ieee.std_logic_1164.all;
 
entity sipo is
 port(
 clk, clear : in std_logic;
 Input_Data: in std_logic;
 Q: out std_logic_vector(3 downto 0) );
end sipo;
 
architecture arch of sipo is

signal shift_reg : std_logic_vector(3 downto 0) := "0000";
 
begin
 
 process (clk)
 begin
 if clear = '1' then
     shift_reg <= "0000";
     Q <= shift_reg;
 elsif (CLK'event and CLK='1') then
     shift_reg(3 downto 1) <= shift_reg(2 downto 0);
     shift_reg(0) <= Input_Data;
     Q <= shift_reg;
 end if;
 end process;
end arch;

sipo_tb.vhdl
library ieee;
use ieee.std_logic_1164.all;
use ieee.numeric_std.all;

entity sipo_tb is
end sipo_tb;

architecture behave of sipo_tb is

component sipo
port (
    clk, clear : in std_logic;
    input_data: in std_logic;
    q : out std_logic_vector(3 downto 0)
);
end component;

-- inputs
signal clk,clear,input_data : std_logic; 

-- outputs
signal q : std_logic_vector(3 downto 0);


begin
-- Instantiate the unit
uut: sipo port map (
    q => q,
    clk => clk,
    clear => clear,
    input_data => input_data
);

-- stimulus process
stim_process: process
begin
clk <= '0';
clear <= '1';
input_data <= '0';
wait for 100 ns;
clk <= '1';
clear <= '1';
input_data <= '0';
wait for 100 ns;
clk <= '0';
clear <= '0';
input_data <= '0';
wait for 100 ns;
clk <= '1';
clear <= '0';
input_data <= '0';
wait for 100 ns;
clk <= '0';
input_data <= '1';
wait for 100 ns;
clk <= '1';
input_data <= '1';
wait for 100 ns;
clk <= '0';
input_data <= '0';
wait for 100 ns;
clk <= '1';
input_data <= '0';
wait for 100 ns;
clk <= '0';
input_data <= '0';
wait for 100 ns;
clk <= '1';
input_data <= '0';
wait for 100 ns;
clk <= '0';
input_data <= '0';
wait for 100 ns;
clk <= '1';
input_data <= '0';
wait for 100 ns;
clk <= '0';
input_data <= '0';
wait for 100 ns;
clk <= '1';
input_data <= '0';
wait for 100 ns;
wait;
end process;
end;

sipo.vcd
$date
  Thu Aug 27 16:17:42 2020
$end
$version
  GHDL v0
$end
$timescale
  1 fs
$end
$scope module standard $end
$upscope $end
$scope module std_logic_1164 $end
$upscope $end
$scope module numeric_std $end
$upscope $end
$scope module sipo_tb $end
$var reg 1 ! clk $end
$var reg 1 " clear $end
$var reg 1 # input_data $end
$var reg 4 $ q[3:0] $end
$scope module uut $end
$var reg 1 % clk $end
$var reg 1 & clear $end
$var reg 1 ' input_data $end
$var reg 4 ( q[3:0] $end
$var reg 4 ) shift_reg[3:0] $end
$upscope $end
$upscope $end
$enddefinitions $end
#0
0!
1"
0#
b0000 $
0%
1&
0'
b0000 (
b0000 )
#100000000
1!
1%
#200000000
0!
0"
0%
0&
#300000000
1!
1%
#400000000
0!
1#
0%
1'
#500000000
1!
1%
b0001 )
#600000000
0!
0#
0%
0'
#700000000
1!
b0001 $
1%
b0001 (
b0010 )
#800000000
0!
0%
#900000000
1!
b0010 $
1%
b0010 (
b0100 )
#1000000000
0!
0%
#1100000000
1!
b0100 $
1%
b0100 (
b1000 )
#1200000000
0!
0%
#1300000000
1!
b1000 $
1%
b1000 (
b0000 )
