sys_zelle.vhdl
LIBRARY ieee;
USE ieee.std_logic_1164.ALL;

ENTITY sys_zelle IS
    PORT (
        clk, reset : IN std_logic;
        links_in, oben_in : IN INTEGER;
        unten_out, rechts_out, ergebnis_out : OUT INTEGER
    );
END ENTITY;

ARCHITECTURE behaviour OF sys_zelle IS
    signal speicher: integer := 0;
BEGIN
    clocking : PROCESS (clk, reset)
    BEGIN
        IF (reset = '1') THEN
            speicher <= 0;
            ergebnis_out <= 0;
            unten_out <= 0; -- korrekt?
            rechts_out <= 0;-- korrekt?
        ELSIF (rising_edge(clk)) THEN
            speicher <= links_in * oben_in + speicher;
            rechts_out <= links_in;
            unten_out <= oben_in;
        END IF;
        ergebnis_out <= speicher;
    END PROCESS;
END ARCHITECTURE;

sys_matrix_3x3.vhdl
LIBRARY IEEE;
USE IEEE.std_logic_1164.ALL;

ENTITY sys_matrix_3x3 IS
    PORT (
        clk, reset : IN std_logic;
        -- Eingabe ist SKALAR!
        -- Kein Array als Eingabe sondern
        -- EIN Input Pro Reihe
        a1, a2, a3, b1, b2, b3 : IN INTEGER;

        -- Ergebnismatrix wird mit je einem Feld definiert
        c11, c12, c13 : OUT INTEGER;
        c21, c22, c23 : OUT INTEGER;
        c31, c32, c33 : OUT INTEGER
    );
END ENTITY;

ARCHITECTURE behaviour OF sys_matrix_3x3 IS
    -- Diese Definition ist NICHT nur auf Testbenches beschränkt
    COMPONENT sys_zelle IS PORT (
        clk, reset : IN std_logic;
        links_in, oben_in : IN INTEGER;
        unten_out, rechts_out, ergebnis_out : OUT INTEGER
        );
    END COMPONENT;

        -- Ausgang jeder Zelle wird als Signal definiert
SIGNAL c11rechts, c11unten, c12rechts, c12unten, c13rechts, c13unten : integer := 0;
SIGNAL c21rechts, c21unten, c22rechts, c22unten, c23rechts, c23unten : integer := 0;
SIGNAL c31rechts, c31unten, c32rechts, c32unten, c33rechts, c33unten : integer := 0;

BEGIN
    sys_zelle_11 : sys_zelle PORT MAP(
        clk => clk, reset => reset,
        links_in => a1, oben_in => b1,
        unten_out => c11unten, rechts_out => c11rechts, 
        ergebnis_out => c11
    );

    sys_zelle_12 : sys_zelle PORT MAP(
        clk => clk, reset => reset,
        links_in => c11rechts, oben_in => b2,
        unten_out => c12unten, rechts_out => c12rechts, 
        ergebnis_out => c12
    );

    sys_zelle_13 : sys_zelle PORT MAP(
        clk => clk, reset => reset,
        links_in => c12rechts, oben_in => b3,
        unten_out => c13unten, rechts_out => c13rechts, 
        ergebnis_out => c13
    );

    sys_zelle_21 : sys_zelle PORT MAP(
        clk => clk, reset => reset,
        links_in => a2, oben_in => c11unten,
        unten_out => c21unten, rechts_out => c21rechts, 
        ergebnis_out => c21
    );

    sys_zelle_22 : sys_zelle PORT MAP(
        clk => clk, reset => reset,
        links_in => c21rechts, oben_in => c12unten,
        unten_out => c22unten, rechts_out => c22rechts, 
        ergebnis_out => c22
    );

    sys_zelle_23 : sys_zelle PORT MAP(
        clk => clk, reset => reset,
        links_in => c22rechts, oben_in => c13unten,
        unten_out => c23unten, rechts_out => c23rechts, 
        ergebnis_out => c23
    );

    sys_zelle_31 : sys_zelle PORT MAP(
        clk => clk, reset => reset,
        links_in => a3, oben_in => c21unten,
        unten_out => c31unten, rechts_out => c31rechts, 
        ergebnis_out => c31
    );

    sys_zelle_32 : sys_zelle PORT MAP(
        clk => clk, reset => reset,
        links_in => c31rechts, oben_in => c22unten,
        unten_out => c32unten, rechts_out => c32rechts, 
        ergebnis_out => c32
    );

    sys_zelle_33 : sys_zelle PORT MAP(
        clk => clk, reset => reset,
        links_in => c32rechts, oben_in => c23unten,
        unten_out => c33unten, rechts_out => c33rechts, 
        ergebnis_out => c33
    );
END ARCHITECTURE;

sys_matrix_3x3_tb_alle_werte_parallel.vhdl
LIBRARY ieee;
USE ieee.std_logic_1164.ALL;

ENTITY sys_matrix_3x3_tb IS
END ENTITY;

ARCHITECTURE test OF sys_matrix_3x3_tb IS
    COMPONENT sys_matrix_3x3 IS PORT (
        clk, reset : IN std_logic;
        -- Eingabe ist SKALAR!
        -- Kein Array als Eingabe sondern
        -- EIN Input Pro Reihe
        a1, a2, a3, b1, b2, b3 : IN INTEGER;

        -- Ergebnismatrix wird mit je einem Feld definiert
        c11, c12, c13 : OUT INTEGER;
        c21, c22, c23 : OUT INTEGER;
        c31, c32, c33 : OUT INTEGER
        );
    END COMPONENT;

    SIGNAL clk, reset : std_logic;
    SIGNAL a1, a2, a3, b1, b2, b3 : INTEGER := 0;

BEGIN
    sys_matrix_3x3_test : sys_matrix_3x3 PORT MAP(
        clk => clk, reset => reset,
        a1 => a1, a2 => a2, a3 => a3,
        b1 => b1, b2 => b2, b3 => b3
    );
    PROCESS BEGIN
        clk <= '0';
        reset <= '1';
        WAIT FOR 10 fs;

        reset <= '0';
        clk <= '1';
        a1 <= 1;
        a2 <= 2;
        a3 <= 3;

        b1 <= 8;
        b2 <= 7;
        b3 <= 6;
        WAIT FOR 10 fs;

        clk <= '0';
        a1 <= 0;
        a2 <= 0;
        a3 <= 0;

        b1 <= 0;
        b2 <= 0;
        b3 <= 0;
        WAIT FOR 10 fs;

        clk <= '1';
        a1 <= 4;
        a2 <= 5;
        a3 <= 6;

        b1 <= 5;
        b2 <= 4;
        b3 <= 3;
        WAIT FOR 10 fs;

        clk <= '0';
        a1 <= 0;
        a2 <= 0;
        a3 <= 0;

        b1 <= 0;
        b2 <= 0;
        b3 <= 0;
        WAIT FOR 10 fs;

        clk <= '1';
        a1 <= 7;
        a2 <= 8;
        a3 <= 9;

        b1 <= 2;
        b2 <= 1;
        b3 <= 0;
        WAIT FOR 10 fs;

        clk <= '0';
        a1 <= 0;
        a2 <= 0;
        a3 <= 0;

        b1 <= 0;
        b2 <= 0;
        b3 <= 0;
        WAIT FOR 10 fs;

        wait;
    END PROCESS;

END ARCHITECTURE;

sys_matrix_3x3_tb.vcd
$date
  Thu Sep 03 13:27:14 2020
$end
$version
  GHDL v0
$end
$timescale
  1 fs
$end
$scope module standard $end
$upscope $end
$scope module std_logic_1164 $end
$upscope $end
$scope module sys_matrix_3x3_tb $end
$var reg 1 ! clk $end
$var reg 1 " reset $end
$var integer 32 # a1 $end
$var integer 32 $ a2 $end
$var integer 32 % a3 $end
$var integer 32 & b1 $end
$var integer 32 ' b2 $end
$var integer 32 ( b3 $end
$scope module sys_matrix_3x3_test $end
$var reg 1 ) clk $end
$var reg 1 * reset $end
$var integer 32 + a1 $end
$var integer 32 , a2 $end
$var integer 32 - a3 $end
$var integer 32 . b1 $end
$var integer 32 / b2 $end
$var integer 32 0 b3 $end
$var integer 32 1 c11 $end
$var integer 32 2 c12 $end
$var integer 32 3 c13 $end
$var integer 32 4 c21 $end
$var integer 32 5 c22 $end
$var integer 32 6 c23 $end
$var integer 32 7 c31 $end
$var integer 32 8 c32 $end
$var integer 32 9 c33 $end
$var integer 32 : c11rechts $end
$var integer 32 ; c11unten $end
$var integer 32 < c12rechts $end
$var integer 32 = c12unten $end
$var integer 32 > c13rechts $end
$var integer 32 ? c13unten $end
$var integer 32 @ c21rechts $end
$var integer 32 A c21unten $end
$var integer 32 B c22rechts $end
$var integer 32 C c22unten $end
$var integer 32 D c23rechts $end
$var integer 32 E c23unten $end
$var integer 32 F c31rechts $end
$var integer 32 G c31unten $end
$var integer 32 H c32rechts $end
$var integer 32 I c32unten $end
$var integer 32 J c33rechts $end
$var integer 32 K c33unten $end
$scope module sys_zelle_11 $end
$var reg 1 L clk $end
$var reg 1 M reset $end
$var integer 32 N links_in $end
$var integer 32 O oben_in $end
$var integer 32 P unten_out $end
$var integer 32 Q rechts_out $end
$var integer 32 R ergebnis_out $end
$var integer 32 S speicher $end
$upscope $end
$scope module sys_zelle_12 $end
$var reg 1 T clk $end
$var reg 1 U reset $end
$var integer 32 V links_in $end
$var integer 32 W oben_in $end
$var integer 32 X unten_out $end
$var integer 32 Y rechts_out $end
$var integer 32 Z ergebnis_out $end
$var integer 32 [ speicher $end
$upscope $end
$scope module sys_zelle_13 $end
$var reg 1 \ clk $end
$var reg 1 ] reset $end
$var integer 32 ^ links_in $end
$var integer 32 _ oben_in $end
$var integer 32 ` unten_out $end
$var integer 32 a rechts_out $end
$var integer 32 b ergebnis_out $end
$var integer 32 c speicher $end
$upscope $end
$scope module sys_zelle_21 $end
$var reg 1 d clk $end
$var reg 1 e reset $end
$var integer 32 f links_in $end
$var integer 32 g oben_in $end
$var integer 32 h unten_out $end
$var integer 32 i rechts_out $end
$var integer 32 j ergebnis_out $end
$var integer 32 k speicher $end
$upscope $end
$scope module sys_zelle_22 $end
$var reg 1 l clk $end
$var reg 1 m reset $end
$var integer 32 n links_in $end
$var integer 32 o oben_in $end
$var integer 32 p unten_out $end
$var integer 32 q rechts_out $end
$var integer 32 r ergebnis_out $end
$var integer 32 s speicher $end
$upscope $end
$scope module sys_zelle_23 $end
$var reg 1 t clk $end
$var reg 1 u reset $end
$var integer 32 v links_in $end
$var integer 32 w oben_in $end
$var integer 32 x unten_out $end
$var integer 32 y rechts_out $end
$var integer 32 z ergebnis_out $end
$var integer 32 { speicher $end
$upscope $end
$scope module sys_zelle_31 $end
$var reg 1 | clk $end
$var reg 1 } reset $end
$var integer 32 !" links_in $end
$var integer 32 "" oben_in $end
$var integer 32 #" unten_out $end
$var integer 32 $" rechts_out $end
$var integer 32 %" ergebnis_out $end
$var integer 32 &" speicher $end
$upscope $end
$scope module sys_zelle_32 $end
$var reg 1 '" clk $end
$var reg 1 (" reset $end
$var integer 32 )" links_in $end
$var integer 32 *" oben_in $end
$var integer 32 +" unten_out $end
$var integer 32 ," rechts_out $end
$var integer 32 -" ergebnis_out $end
$var integer 32 ." speicher $end
$upscope $end
$scope module sys_zelle_33 $end
$var reg 1 /" clk $end
$var reg 1 0" reset $end
$var integer 32 1" links_in $end
$var integer 32 2" oben_in $end
$var integer 32 3" unten_out $end
$var integer 32 4" rechts_out $end
$var integer 32 5" ergebnis_out $end
$var integer 32 6" speicher $end
$upscope $end
$upscope $end
$upscope $end
$enddefinitions $end
#0
0!
1"
b0 #
b0 $
b0 %
b0 &
b0 '
b0 (
0)
1*
b0 +
b0 ,
b0 -
b0 .
b0 /
b0 0
b0 1
b0 2
b0 3
b0 4
b0 5
b0 6
b0 7
b0 8
b0 9
b0 :
b0 ;
b0 <
b0 =
b0 >
b0 ?
b0 @
b0 A
b0 B
b0 C
b0 D
b0 E
b0 F
b0 G
b0 H
b0 I
b0 J
b0 K
0L
1M
b0 N
b0 O
b0 P
b0 Q
b0 R
b0 S
0T
1U
b0 V
b0 W
b0 X
b0 Y
b0 Z
b0 [
0\
1]
b0 ^
b0 _
b0 `
b0 a
b0 b
b0 c
0d
1e
b0 f
b0 g
b0 h
b0 i
b0 j
b0 k
0l
1m
b0 n
b0 o
b0 p
b0 q
b0 r
b0 s
0t
1u
b0 v
b0 w
b0 x
b0 y
b0 z
b0 {
0|
1}
b0 !"
b0 ""
b0 #"
b0 $"
b0 %"
b0 &"
0'"
1("
b0 )"
b0 *"
b0 +"
b0 ,"
b0 -"
b0 ."
0/"
10"
b0 1"
b0 2"
b0 3"
b0 4"
b0 5"
b0 6"
#10
1!
0"
b1 #
b1000 &
1)
0*
b1 +
b1000 .
b1 :
b1000 ;
1L
0M
b1 N
b1000 O
b1000 P
b1 Q
b1000 S
1T
0U
b1 V
1\
0]
1d
0e
b1000 g
1l
0m
1t
0u
1|
0}
1'"
0("
1/"
00"
#20
0!
b0 #
b0 &
0)
b0 +
b0 .
b1000 1
0L
b0 N
b0 O
b1000 R
0T
0\
0d
0l
0t
0|
0'"
0/"
#30
1!
b10 #
b100 $
b101 &
b111 '
1)
b10 +
b100 ,
b101 .
b111 /
b10 :
b101 ;
b1 <
b111 =
b100 @
b1000 A
1L
b10 N
b101 O
b101 P
b10 Q
b10010 S
1T
b10 V
b111 W
b111 X
b1 Y
b111 [
1\
b1 ^
1d
b100 f
b101 g
b1000 h
b100 i
b100000 k
1l
b100 n
b111 o
1t
1|
b1000 ""
1'"
1/"
#40
0!
b0 #
b0 $
b0 &
b0 '
0)
b0 +
b0 ,
b0 .
b0 /
b10010 1
b111 2
b100000 4
0L
b0 N
b0 O
b10010 R
0T
b0 W
b111 Z
0\
0d
b0 f
b100000 j
0l
0t
0|
0'"
0/"
#50
1!
b11 #
b101 $
b111 %
b10 &
b100 '
b110 (
1)
b11 +
b101 ,
b111 -
b10 .
b100 /
b110 0
b11 :
b10 ;
b10 <
b100 =
b1 >
b110 ?
b101 @
b101 A
b100 B
b111 C
b111 F
b1000 G
1L
b11 N
b10 O
b10 P
b11 Q
b11000 S
1T
b11 V
b100 W
b100 X
b10 Y
b1111 [
1\
b10 ^
b110 _
b110 `
b1 a
b110 c
1d
b101 f
b10 g
b101 h
b101 i
b111001 k
1l
b101 n
b100 o
b111 p
b100 q
b11100 s
1t
b100 v
b110 w
1|
b111 !"
b101 ""
b1000 #"
b111 $"
b111000 &"
1'"
b111 )"
b111 *"
1/"
#60
0!
b0 #
b0 $
b0 %
b0 &
b0 '
b0 (
0)
b0 +
b0 ,
b0 -
b0 .
b0 /
b0 0
b11000 1
b1111 2
b110 3
b111001 4
b11100 5
b111000 7
0L
b0 N
b0 O
b11000 R
0T
b0 W
b1111 Z
0\
b0 _
b110 b
0d
b0 f
b111001 j
0l
b11100 r
0t
0|
b0 !"
b111000 %"
0'"
0/"
#70
1!
b110 $
b1000 %
b1 '
b11 (
1)
b110 ,
b1000 -
b1 /
b11 0
b0 :
b0 ;
b11 <
b1 =
b10 >
b11 ?
b110 @
b10 A
b101 B
b100 C
b100 D
b110 E
b1000 F
b101 G
b111 H
b111 I
1L
b0 P
b0 Q
1T
b0 V
b1 W
b1 X
b11 Y
b10010 [
1\
b11 ^
b11 _
b11 `
b10 a
b1100 c
1d
b110 f
b0 g
b10 h
b110 i
b1000101 k
1l
b110 n
b1 o
b100 p
b101 q
b110000 s
1t
b101 v
b11 w
b110 x
b100 y
b11000 {
1|
b1000 !"
b10 ""
b101 #"
b1000 $"
b1100000 &"
1'"
b1000 )"
b100 *"
b111 +"
b111 ,"
b110001 ."
1/"
b111 1"
b110 2"
#80
0!
b0 $
b0 %
b0 '
b0 (
0)
b0 ,
b0 -
b0 /
b0 0
b10010 2
b1100 3
b1000101 4
b110000 5
b11000 6
b1100000 7
b110001 8
0L
0T
b0 W
b10010 Z
0\
b0 _
b1100 b
0d
b0 f
b1000101 j
0l
b110000 r
0t
b11000 z
0|
b0 !"
b1100000 %"
0'"
b110001 -"
0/"
#90
1!
b1001 %
1)
b1001 -
b0 <
b0 =
b11 >
b0 ?
b0 @
b0 A
b110 B
b1 C
b101 D
b11 E
b1001 F
b10 G
b1000 H
b100 I
b111 J
b110 K
1L
1T
b0 X
b0 Y
1\
b0 ^
b0 `
b11 a
1d
b0 h
b0 i
1l
b0 n
b0 o
b1 p
b110 q
b110110 s
1t
b110 v
b0 w
b11 x
b101 y
b100111 {
1|
b1001 !"
b0 ""
b10 #"
b1001 $"
b1110010 &"
1'"
b1001 )"
b1 *"
b100 +"
b1000 ,"
b1010001 ."
1/"
b1000 1"
b11 2"
b110 3"
b111 4"
b101010 6"
#100
0!
b0 %
0)
b0 -
b110110 5
b100111 6
b1110010 7
b1010001 8
b101010 9
0L
0T
0\
0d
0l
b110110 r
0t
b100111 z
0|
b0 !"
b1110010 %"
0'"
b1010001 -"
0/"
b101010 5"
#110
1!
1)
b0 >
b0 B
b0 C
b110 D
b0 E
b0 F
b0 G
b1001 H
b1 I
b1000 J
b11 K
1L
1T
1\
b0 a
1d
1l
b0 p
b0 q
1t
b0 v
b0 x
b110 y
1|
b0 #"
b0 $"
1'"
b0 )"
b0 *"
b1 +"
b1001 ,"
b1011010 ."
1/"
b1001 1"
b0 2"
b11 3"
b1000 4"
b1000010 6"
#120
0!
0)
b1011010 8
b1000010 9
0L
0T
0\
0d
0l
0t
0|
0'"
b1011010 -"
0/"
b1000010 5"
